vippool/__init__.py
vippool/storage.py
vippool_storage-1.1.6.dist-info/LICENSE
vippool_storage-1.1.6.dist-info/METADATA
vippool_storage-1.1.6.dist-info/WHEEL
vippool_storage-1.1.6.dist-info/top_level.txt
vippool_storage-1.1.6.dist-info/RECORD
