Metadata-Version: 2.1
Name: vippool-storage
Version: 1.1.6
Summary: A simple interface for the block chain
Home-page: https://github.com/vippool/storage
Author: VIPPOOL Inc.
Author-email: dev-team@vippool.net
License: UNKNOWN
Keywords: blockchain
Platform: UNKNOWN
Classifier: Intended Audience :: Developers
Classifier: License :: OSI Approved :: MIT License
Classifier: Programming Language :: Python :: 2
Classifier: Programming Language :: Python :: 2.7
Classifier: Programming Language :: Python :: 3
Classifier: Programming Language :: Python :: 3.5
Classifier: Programming Language :: Python :: 3.8
Requires-Dist: future
Requires-Dist: six
